embed_toolkit/__init__.py
embed_toolkit/magview.py
embed_toolkit/utilities.py
embed_toolkit-0.2.10.dist-info/METADATA
embed_toolkit-0.2.10.dist-info/WHEEL
embed_toolkit-0.2.10.dist-info/top_level.txt
embed_toolkit-0.2.10.dist-info/RECORD
