Metadata-Version: 2.4
Name: embed-toolkit
Version: 0.2.10
Requires-Dist: pandas>=2.2
